<?xml version="1.0" encoding="utf-16"?>
<adv file="spyceadvfile">
  <info>
    <VoiceCueSheet value="AdvVoice/3018010401" />
  </info>
  <command>
    <Start />
    <load_cue_sheet />
    <sound type="Bgm" cue_name="Adv1" />
    <bg show="True" resource_type="Background" file="02_wasabimo_001" color="#ffffffff" effect="Immediately" effect_time="0.3" wait="False" />
    <char_spine_animation obj_id="青葉 初芽" face_anim_type="020_Facial_thinking" body_anim_type="12_DropShoulders" force_end="False" loop="True" />
    <msg window_type="SystemMsg" text="ハロウィン通り魔事件を解決し、&#xA;ソラサキハロウィンも終わった数日後……。" stop="True" />
    <create type="Character" obj_id="高坂 信" data_id="311010003" x="200" y="0" anchor="Bottom" />
    <create type="Character" obj_id="青葉 初芽" data_id="311005005" x="-200" y="0" anchor="Bottom" />
    <char_spine_animation obj_id="高坂 信" face_anim_type="003_Facial_laugh" body_anim_type="06_ChestLeftHand" force_end="False" loop="True" />
    <char_spine_animation obj_id="青葉 初芽" face_anim_type="020_Facial_thinking" body_anim_type="12_DropShoulders" force_end="False" loop="True" />
    <msg speaker="高坂 信" text="こんにちはー。" speaker_show="True" stop="True" voice="ks11010_02_0303" />
    <char_spine_animation body_anim_type="03_BackBothHands" force_end="False" loop="True" />
    <msg speaker="青葉 初芽" text="……。" speaker_show="True" stop="True" voice="ah11005_02_0635" />
    <delete obj_id="青葉 初芽" />
    <create type="Character" obj_id="カトリーナ" data_id="311009003" x="-300" y="0" anchor="Bottom" />
    <move obj_id="カトリーナ" x_move_type="MoveTo" y_move_type="MoveValue" time="0.3" wait="False" />
    <move obj_id="高坂 信" x="300" x_move_type="MoveTo" y_move_type="MoveValue" time="0.5" wait="False" />
    <char_spine_animation obj_id="カトリーナ" face_anim_type="003_Facial_laugh" body_anim_type="09_PutHands" force_end="False" loop="True" />
    <msg speaker="カトリーナ" text="この声は、シン様!!" speaker_show="True" stop="True" voice="kt11009_02_0219" />
    <char_spine_animation obj_id="高坂 信" face_anim_type="011_Facial_surprise" body_anim_type="16_BendBackward" force_end="False" loop="True" />
    <msg speaker="高坂 信" text="うわわ、急に飛び出してくるから、&#xA;びっくりしたよ！" speaker_show="True" stop="True" voice="ks11010_02_0304" />
    <move obj_id="カトリーナ" x="-200" x_move_type="MoveTo" y_move_type="MoveValue" time="0.3" wait="False" />
    <move obj_id="高坂 信" x="200" x_move_type="MoveTo" y_move_type="MoveValue" time="0.3" wait="True" />
    <char_spine_animation obj_id="カトリーナ" face_anim_type="003_Facial_laugh" body_anim_type="09_PutHands" force_end="False" loop="True" />
    <msg speaker="カトリーナ" text="今日もシン様の愛くるしいお姿を見ることができて、&#xA;１日をハッピーに生きていけそうです♪" speaker_show="True" stop="True" voice="kt11009_02_0220" />
    <char_spine_animation obj_id="高坂 信" face_anim_type="020_Facial_thinking" body_anim_type="03_BackBothHands" force_end="False" loop="True" />
    <msg speaker="高坂 信" text="いつも大袈裟だなぁ、カトさんは。" speaker_show="True" stop="True" voice="ks11010_02_0305" />
    <move obj_id="カトリーナ" x="0" x_move_type="MoveTo" y_move_type="MoveValue" time="0.3" wait="False" />
    <move obj_id="高坂 信" x="300" x_move_type="MoveTo" y_move_type="MoveValue" time="0.3" wait="False" />
    <create type="Character" obj_id="青葉 初芽" data_id="311005005" x="-400" y="0" anchor="Bottom" />
    <move obj_id="青葉 初芽" x="-300" x_move_type="MoveTo" y_move_type="MoveValue" time="0.3" wait="True" />
    <char_spine_animation obj_id="カトリーナ" face_anim_type="008_Facial_serious" body_anim_type="15_Negative" force_end="False" loop="False" />
    <char_spine_animation obj_id="青葉 初芽" face_anim_type="020_Facial_thinking" body_anim_type="03_BackBothHands" force_end="False" loop="True" />
    <msg speaker="カトリーナ" text="いえいえ、大袈裟などでは――" speaker_show="True" stop="True" voice="kt11009_02_0221" />
    <char_spine_animation obj_id="青葉 初芽" force_end="False" loop="True" />
    <char_spine_animation obj_id="カトリーナ" face_anim_type="005_Facial_sad" body_anim_type="13_Question" force_end="False" loop="True" />
    <msg speaker="カトリーナ" text="あら？　どうしたの、初芽ちゃん。&#xA;元気がないみたいだけど……。" speaker_show="True" stop="True" voice="kt11009_02_0222" />
    <char_spine_animation obj_id="青葉 初芽" face_anim_type="011_Facial_surprise" body_anim_type="06_ChestLeftHand" force_end="False" loop="False" />
    <msg speaker="青葉 初芽" text="あ、いえ！&#xA;気にしないでください。" speaker_show="True" stop="True" voice="ah11005_02_0636" />
    <delete obj_id="高坂 信" />
    <move obj_id="青葉 初芽" x="-200" x_move_type="MoveTo" y_move_type="MoveValue" time="0.3" wait="False" />
    <move obj_id="カトリーナ" x="200" x_move_type="MoveTo" y_move_type="MoveValue" time="0.3" wait="True" />
    <char_spine_animation obj_id="青葉 初芽" face_anim_type="020_Facial_thinking" body_anim_type="12_DropShoulders" force_end="False" loop="True" />
    <msg speaker="青葉 初芽" text="はぁ……。" speaker_show="True" stop="True" voice="ah11005_02_0637" />
    <char_spine_animation obj_id="カトリーナ" face_anim_type="008_Facial_serious" body_anim_type="11_Point" force_end="False" loop="True" />
    <msg speaker="カトリーナ" text="気にしないでって言われても……&#xA;ため息までついてるじゃない。" speaker_show="True" stop="True" voice="kt11009_02_0223" />
    <move obj_id="青葉 初芽" x="-300" x_move_type="MoveTo" y_move_type="MoveValue" time="0.3" wait="False" />
    <move obj_id="カトリーナ" x="0" x_move_type="MoveTo" y_move_type="MoveValue" time="0.3" wait="False" />
    <create type="Character" obj_id="石川 五恵" data_id="311006007" x="400" y="0" anchor="Bottom" />
    <move obj_id="石川 五恵" x="300" x_move_type="MoveTo" y_move_type="MoveValue" time="0.5" wait="True" />
    <char_spine_animation obj_id="石川 五恵" face_anim_type="002_Facial_smile" body_anim_type="03_BackBothHands" force_end="False" loop="True" />
    <msg speaker="石川 五恵" text="あれ？　師匠、来てるんですか？" speaker_show="True" stop="True" voice="ig11006_02_0372" />
    <char_spine_animation obj_id="青葉 初芽" face_anim_type="009_Facial_blush" force_end="False" loop="True" />
    <msg speaker="青葉 初芽" text="ごえちゃん……。" speaker_show="True" stop="True" voice="ah11005_02_0638" />
    <delete obj_id="カトリーナ" />
    <move obj_id="石川 五恵" x="0" x_move_type="MoveTo" y_move_type="MoveValue" time="0.3" wait="True" />
    <create type="Character" obj_id="高坂 信" data_id="311010003" x="400" y="0" anchor="Bottom" />
    <move obj_id="高坂 信" x="300" x_move_type="MoveTo" y_move_type="MoveValue" time="0.5" wait="True" />
    <char_spine_animation obj_id="高坂 信" face_anim_type="002_Facial_smile" body_anim_type="06_ChestLeftHand" force_end="False" loop="True" />
    <msg speaker="高坂 信" text="あ、今日は五恵ちゃんもバイトで入ってるんだね。" speaker_show="True" stop="True" voice="ks11010_02_0306" />
    <char_spine_animation obj_id="石川 五恵" face_anim_type="002_Facial_smile" body_anim_type="20_PositiveDouble" force_end="False" loop="False" />
    <msg speaker="石川 五恵" text="はい。" speaker_show="True" stop="True" voice="ig11006_02_0373" />
    <char_spine_animation obj_id="青葉 初芽" face_anim_type="020_Facial_thinking" body_anim_type="12_DropShoulders" force_end="False" loop="True" />
    <msg speaker="青葉 初芽" text="はぁぁ～……。" speaker_show="True" stop="True" voice="ah11005_02_0639" />
    <char_spine_animation obj_id="石川 五恵" face_anim_type="005_Facial_sad" body_anim_type="13_Question" force_end="False" loop="True" />
    <msg speaker="石川 五恵" text="どうしたんですか、師匠？" speaker_show="True" stop="True" voice="ig11006_02_0374" />
    <char_spine_animation obj_id="高坂 信" face_anim_type="008_Facial_serious" body_anim_type="18_ArmsCrossed" force_end="False" loop="True" />
    <msg speaker="高坂 信" text="これは重症だね……。" speaker_show="True" stop="True" voice="ks11010_02_0307" />
    <delete obj_id="石川 五恵" />
    <delete obj_id="青葉 初芽" />
    <delete obj_id="高坂 信" />
    <create type="Character" obj_id="カトリーナ" data_id="311009003" x="0" y="0" anchor="Bottom" />
    <char_spine_animation obj_id="カトリーナ" face_anim_type="005_Facial_sad" body_anim_type="13_Question" force_end="False" loop="True" />
    <msg speaker="カトリーナ" text="発明の失敗でもしたの？" speaker_show="True" stop="True" voice="kt11009_02_0224" />
    <delete obj_id="カトリーナ" />
    <create type="Character" obj_id="石川 五恵" data_id="311006007" x="200" y="0" anchor="Bottom" />
    <create type="Character" obj_id="青葉 初芽" data_id="311005005" x="-200" y="0" anchor="Bottom" />
    <char_spine_animation obj_id="青葉 初芽" face_anim_type="020_Facial_thinking" body_anim_type="12_DropShoulders" force_end="False" loop="True" />
    <char_spine_animation obj_id="石川 五恵" face_anim_type="008_Facial_serious" body_anim_type="09_PutHands" force_end="False" loop="True" />
    <msg speaker="石川 五恵" text="私でよければ、いつでも実験台になりますよ！" speaker_show="True" stop="True" voice="ig11006_02_0375" />
    <char_spine_animation obj_id="青葉 初芽" face_anim_type="016_Facial_smileBitter" body_anim_type="14_Positive" force_end="False" loop="False" />
    <msg speaker="青葉 初芽" text="ありがとう、ごえちゃん。&#xA;でも……違うんです。発明のことではなく……。" speaker_show="True" stop="True" voice="ah11005_02_0640" />
    <move obj_id="青葉 初芽" x="-300" x_move_type="MoveTo" y_move_type="MoveValue" time="0.3" wait="False" />
    <move obj_id="石川 五恵" x="0" x_move_type="MoveTo" y_move_type="MoveValue" time="0.3" wait="False" />
    <create type="Character" obj_id="高坂 信" data_id="311010003" x="400" y="0" anchor="Bottom" />
    <move obj_id="高坂 信" x="300" x_move_type="MoveTo" y_move_type="MoveValue" time="0.5" wait="True" />
    <char_spine_animation obj_id="高坂 信" face_anim_type="005_Facial_sad" body_anim_type="03_BackBothHands" force_end="False" loop="True" />
    <msg speaker="高坂 信" text="初芽ちゃんってば、ハロウィンの時のことで&#xA;落ち込んでるみたいで。" speaker_show="True" stop="True" voice="ks11010_02_0308" />
    <char_spine_animation obj_id="石川 五恵" face_anim_type="005_Facial_sad" body_anim_type="12_DropShoulders" force_end="False" loop="True" />
    <msg speaker="石川 五恵" text="何かあったんですか？&#xA;まさか……赤星さんの調査にミスがあったとか……。" speaker_show="True" stop="True" voice="ig11006_02_0376" />
    <char_spine_animation obj_id="青葉 初芽" face_anim_type="020_Facial_thinking" body_anim_type="15_Negative" force_end="False" loop="False" />
    <msg speaker="青葉 初芽" text="違います。&#xA;私は……私は……" speaker_show="True" stop="True" voice="ah11005_02_0641" />
    <char_spine_animation obj_id="青葉 初芽" face_anim_type="017_Facial_shock" body_anim_type="09_PutHands" force_end="False" loop="True" />
    <msg speaker="青葉 初芽" text="なんであの時、ごえちゃんの写真を、&#xA;もっとたくさん撮っていなかったんでしょう!?" speaker_show="True" stop="True" voice="ah11005_02_0642" />
    <char_spine_animation obj_id="石川 五恵" face_anim_type="011_Facial_surprise" body_anim_type="06_ChestLeftHand" force_end="False" loop="True" />
    <msg speaker="石川 五恵" text="……え？" speaker_show="True" stop="True" voice="ig11006_02_0377" />
    <char_spine_animation obj_id="青葉 初芽" face_anim_type="005_Facial_sad" body_anim_type="11_Point" force_end="False" loop="True" />
    <msg speaker="青葉 初芽" text="ごえちゃんがあんな格好をすることなんて&#xA;滅多にないんですよ！" speaker_show="True" stop="True" voice="ah11005_02_0643" />
    <char_spine_animation obj_id="青葉 初芽" face_anim_type="020_Facial_thinking" body_anim_type="18_ArmsCrossed" force_end="False" loop="True" />
    <msg speaker="青葉 初芽" text="なのに、写真は数枚だけですし、&#xA;考えてみたら、私と一緒に写った写真もありません!!" speaker_show="True" stop="True" voice="ah11005_02_0644" />
    <char_spine_animation obj_id="高坂 信" face_anim_type="009_Facial_blush" body_anim_type="03_BackBothHands" force_end="False" loop="True" />
    <msg speaker="高坂 信" text="――というわけらしいんだ。" speaker_show="True" stop="True" voice="ks11010_02_0309" />
    <delete obj_id="高坂 信" />
    <delete obj_id="青葉 初芽" />
    <delete obj_id="石川 五恵" />
    <create type="Character" obj_id="カトリーナ" data_id="311009003" x="0" y="0" anchor="Bottom" />
    <char_spine_animation obj_id="カトリーナ" face_anim_type="003_Facial_laugh" body_anim_type="11_Point" force_end="False" loop="True" />
    <msg speaker="カトリーナ" text="そういうことね。&#xA;だったら、私にいいアイデアがあるわ。" speaker_show="True" stop="True" voice="kt11009_02_0225" />
    <char_spine_animation obj_id="カトリーナ" face_anim_type="002_Facial_smile" body_anim_type="09_PutHands" force_end="False" loop="True" />
    <msg speaker="カトリーナ" text="衣装はあるんだし、せっかくだからごえちゃんを&#xA;モデルにした撮影会を開くのはどうかしら？" speaker_show="True" stop="True" voice="kt11009_02_0226" />
    <move obj_id="カトリーナ" x="300" x_move_type="MoveTo" y_move_type="MoveValue" time="0.3" wait="True" />
    <create type="Character" obj_id="石川 五恵" data_id="311006007" x="-400" y="0" anchor="Bottom" />
    <create type="Character" obj_id="青葉 初芽" data_id="311005005" x="-100" y="0" anchor="Bottom" />
    <move obj_id="石川 五恵" x="-300" x_move_type="MoveTo" y_move_type="MoveValue" time="0.5" wait="False" />
    <move obj_id="青葉 初芽" x="0" x_move_type="MoveTo" y_move_type="MoveValue" time="0.5" wait="True" />
    <char_spine_animation obj_id="石川 五恵" face_anim_type="011_Facial_surprise" body_anim_type="16_BendBackward" force_end="False" loop="True" />
    <msg speaker="石川 五恵" text="え？" speaker_show="True" stop="True" voice="ig11006_02_0378" />
    <char_spine_animation obj_id="青葉 初芽" face_anim_type="008_Facial_serious" body_anim_type="07_ChestBothHands" force_end="False" loop="True" />
    <msg speaker="青葉 初芽" text="なるほど、それはグッドアイデアですね！&#xA;さすが師匠!!" speaker_show="True" stop="True" voice="ah11005_02_0645" />
    <char_spine_animation obj_id="カトリーナ" face_anim_type="018_Facial_smug" body_anim_type="14_Positive" force_end="False" loop="False" />
    <msg speaker="カトリーナ" text="弟子と孫弟子のためだもの。&#xA;いいアイデアだって出てくるわ。" speaker_show="True" stop="True" voice="kt11009_02_0227" />
    <char_spine_animation obj_id="青葉 初芽" face_anim_type="003_Facial_laugh" body_anim_type="09_PutHands" force_end="False" loop="True" />
    <msg speaker="青葉 初芽" text="ハロウィン衣装もですし、他にも着てほしい衣装が&#xA;ありますし、楽しい撮影会になりそうです！" speaker_show="True" stop="True" voice="ah11005_02_0646" />
    <delete obj_id="カトリーナ" />
    <delete obj_id="青葉 初芽" />
    <move obj_id="石川 五恵" x="-200" x_move_type="MoveTo" y_move_type="MoveValue" time="0.3" wait="True" />
    <create type="Character" obj_id="高坂 信" data_id="311010003" x="300" y="0" anchor="Bottom" />
    <move obj_id="高坂 信" x="200" x_move_type="MoveTo" y_move_type="MoveValue" time="0.5" wait="True" />
    <char_spine_animation obj_id="高坂 信" face_anim_type="008_Facial_serious" body_anim_type="13_Question" force_end="False" loop="True" />
    <msg speaker="高坂 信" text="ご、ごえちゃん、大丈夫……？&#xA;勝手に話が進んでいってるけど……。" speaker_show="True" stop="True" voice="ks11010_02_0310" />
    <char_spine_animation obj_id="石川 五恵" face_anim_type="009_Facial_blush" body_anim_type="19_Amazed" force_end="False" loop="True" />
    <msg speaker="石川 五恵" text="あ、ええっと……&#xA;撮影会はちょっと恥ずかしいですけど……" speaker_show="True" stop="True" voice="ig11006_02_0379" />
    <char_spine_animation obj_id="石川 五恵" face_anim_type="003_Facial_laugh" body_anim_type="09_PutHands" force_end="False" loop="True" />
    <msg speaker="石川 五恵" text="でも、師匠が喜んでくれるなら、私も幸せだから、&#xA;やりたいです。" speaker_show="True" stop="True" voice="ig11006_02_0380" />
    <char_spine_animation obj_id="高坂 信" face_anim_type="002_Facial_smile" body_anim_type="03_BackBothHands" force_end="False" loop="True" />
    <msg speaker="高坂 信" text="ごえちゃんは本当に健気だねえ……。" speaker_show="True" stop="True" voice="ks11010_02_0311" />
    <msg_window_show show="False" />
    <fade_out time="0.5" type="Default" wait="True" />
    <sound_stop cue_name="Adv1" />
  </command>
</adv>